COPYING
MANIFEST.in
Makefile
README.md
setup.py
stepic.1
stepic.help2man_include
doc/help.txt
doc/index.html
doc/pydoc/stepic.html
stepic/__init__.py
stepic.egg-info/PKG-INFO
stepic.egg-info/SOURCES.txt
stepic.egg-info/dependency_links.txt
stepic.egg-info/entry_points.txt
stepic.egg-info/not-zip-safe
stepic.egg-info/requires.txt
stepic.egg-info/top_level.txt
tests/test_img.png
tests/test_text.txt
tests/tests.py