Metadata-Version: 2.1
Name: stepic
Version: 0.5.0
Summary: Python image steganography
Home-page: https://launchpad.net/stepic
Author: Lenny Domnitser
Author-email: lenny@domnit.org
Maintainer: Scott Kitterman
Maintainer-email: scott@kitterman.com
License: GPL
Platform: UNKNOWN
Classifier: License :: OSI Approved :: GNU General Public License v2 or later (GPLv2+)
Classifier: Environment :: Console
Classifier: Topic :: Multimedia :: Graphics
Classifier: Topic :: Utilities
Classifier: Development Status :: 6 - Mature
Classifier: Programming Language :: Python :: 3 :: Only
